dco/__init__.py
dco/cli.py
dco/core.py
dco/secrets.py
dco/utils.py
dco/watcher.py
dco-0.0.5.dist-info/licenses/LICENSE
dco-0.0.5.dist-info/METADATA
dco-0.0.5.dist-info/WHEEL
dco-0.0.5.dist-info/entry_points.txt
dco-0.0.5.dist-info/top_level.txt
dco-0.0.5.dist-info/RECORD
