Metadata-Version: 2.4
Name: dco
Version: 0.0.5
Summary: Dynamic Config Orchestrator - layered typed configuration loader
Home-page: https://github.com/safvan041/DCO
Author: safwan bakkar
Author-email: Safwan Bakkar <safwanbakkar.dev@hotmail.com>
License: MIT
Requires-Python: >=3.9
License-File: LICENSE
Requires-Dist: pydantic>=1.10
Requires-Dist: python-dotenv>=0.21
Requires-Dist: PyYAML>=6.0
Requires-Dist: watchdog>=3.0
Requires-Dist: boto3>=1.26
Requires-Dist: jsonschema>=4.0
Requires-Dist: types-PyYAML>=6.0
Dynamic: license-file
